aiorussound/__init__.py
aiorussound/connection.py
aiorussound/const.py
aiorussound/exceptions.py
aiorussound/models.py
aiorussound/py.typed
aiorussound/rio.py
aiorussound/util.py
aiorussound-4.9.0.dist-info/METADATA
aiorussound-4.9.0.dist-info/WHEEL
aiorussound-4.9.0.dist-info/licenses/LICENSE
aiorussound-4.9.0.dist-info/RECORD
