Metadata-Version: 2.4
Name: aiorussound
Version: 4.9.0
Summary: Asyncio client for Russound RIO devices.
License-Expression: MIT
License-File: LICENSE
Author: Noah Husby
Author-email: opensource@husbylabs.com
Maintainer: Noah Husby
Maintainer-email: opensource@husbylabs.com
Requires-Python: >=3.11
Classifier: Programming Language :: Python :: 3
Classifier: Programming Language :: Python :: 3.11
Classifier: Programming Language :: Python :: 3.12
Classifier: Programming Language :: Python :: 3.13
Classifier: Programming Language :: Python :: 3.14
Provides-Extra: dev
Provides-Extra: docs
Requires-Dist: coverage (==7.10.6) ; extra == "dev"
Requires-Dist: mashumaro (>=3.17)
Requires-Dist: mypy (==1.18.1) ; extra == "dev"
Requires-Dist: orjson (>=3.9.0)
Requires-Dist: pdoc (>=14.7,<16.0) ; extra == "docs"
Requires-Dist: pre-commit (==4.3.0) ; extra == "dev"
Requires-Dist: pre-commit-hooks (==6.0.0) ; extra == "dev"
Requires-Dist: pylint (==4.0.0) ; extra == "dev"
Requires-Dist: pyserial-asyncio-fast (>=0.16)
Requires-Dist: pytest (==8.4.2) ; extra == "dev"
Requires-Dist: pytest-asyncio (==1.2.0) ; extra == "dev"
Requires-Dist: pytest-cov (==7.0.0) ; extra == "dev"
Requires-Dist: ruff (==0.14.0) ; extra == "dev"
Project-URL: Documentation, https://github.com/noahhusby/aiorussound
Project-URL: Homepage, https://github.com/noahhusby/aiorussound
Project-URL: Repository, https://github.com/noahhusby/aiorussound
